firestone_lib/__init__.py
firestone_lib/cli.py
firestone_lib/resource.py
firestone_lib/resources/__init__.py
firestone_lib/resources/logging/__init__.py
firestone_lib/resources/logging/cli.conf
firestone_lib/utils.py
firestone_lib-0.2.4.dist-info/METADATA
firestone_lib-0.2.4.dist-info/WHEEL
firestone_lib-0.2.4.dist-info/licenses/LICENSE
firestone_lib-0.2.4.dist-info/RECORD
