Metadata-Version: 2.4
Name: firestone-lib
Version: 0.2.4
Summary: Library to help build OpenAPI, AsyncAPI and gRPC specs based off one or more resource json schema files
License: Apache 2.0
License-File: LICENSE
Author: Erick Bourgeois
Author-email: erick@jeb.ca
Requires-Python: >=3.9,<4.0
Classifier: License :: Other/Proprietary License
Classifier: Programming Language :: Python :: 3
Classifier: Programming Language :: Python :: 3.9
Classifier: Programming Language :: Python :: 3.10
Classifier: Programming Language :: Python :: 3.11
Classifier: Programming Language :: Python :: 3.12
Classifier: Programming Language :: Python :: 3.13
Classifier: Programming Language :: Python :: 3.14
Requires-Dist: Jinja2 (>=3.1.2)
Requires-Dist: click (>=8.1.3)
Requires-Dist: jsonref (>=1.0.1)
Requires-Dist: jsonschema (>=4.17.3)
Requires-Dist: pyyaml (>=6.0)
